{
  "text": "ἄρα οὖν ὃν θέλει ἐλεεῖ, ὃν δὲ θέλει σκληρύνει.",
  "words": [
    {
      "position": 1,
      "text": "ἄρα",
      "lemma": [
        "G0686"
      ],
      "morph": "robinson:CONJ",
      "strongs": "G0686",
      "translation": "So",
      "metadata": {},
      "gematria": {
        "standard": 102,
        "ordinal": 19,
        "reduced": 3
      }
    },
    {
      "position": 2,
      "text": "οὖν",
      "lemma": [
        "G3767"
      ],
      "morph": "robinson:CONJ",
      "strongs": "G3767",
      "translation": "then",
      "metadata": {},
      "gematria": {
        "standard": 520,
        "ordinal": 48,
        "reduced": 7
      }
    },
    {
      "position": 3,
      "text": "ὃν",
      "lemma": [
        "G3739"
      ],
      "morph": "robinson:R-ASM",
      "strongs": "G3739",
      "translation": "to whom",
      "metadata": {},
      "gematria": {
        "standard": 120,
        "ordinal": 28,
        "reduced": 3
      }
    },
    {
      "position": 4,
      "text": "θέλει",
      "lemma": [
        "G2309"
      ],
      "morph": "robinson:V-PAI-3S",
      "strongs": "G2309",
      "translation": "He wants",
      "metadata": {},
      "gematria": {
        "standard": 59,
        "ordinal": 38,
        "reduced": 5
      }
    },
    {
      "position": 5,
      "text": "ἐλεεῖ,",
      "lemma": [
        "G1653"
      ],
      "morph": "robinson:V-PAI-3S",
      "strongs": "G1653",
      "translation": "He shows mercy,",
      "metadata": {},
      "gematria": {
        "standard": 55,
        "ordinal": 35,
        "reduced": 1
      }
    },
    {
      "position": 6,
      "text": "ὃν",
      "lemma": [
        "G3739"
      ],
      "morph": "robinson:R-ASM",
      "strongs": "G3739",
      "translation": "whom",
      "metadata": {},
      "gematria": {
        "standard": 120,
        "ordinal": 28,
        "reduced": 3
      }
    },
    {
      "position": 7,
      "text": "δὲ",
      "lemma": [
        "G1161"
      ],
      "morph": "robinson:CONJ",
      "strongs": "G1161",
      "translation": "now",
      "metadata": {},
      "gematria": {
        "standard": 9,
        "ordinal": 9,
        "reduced": 9
      }
    },
    {
      "position": 8,
      "text": "θέλει",
      "lemma": [
        "G2309"
      ],
      "morph": "robinson:V-PAI-3S",
      "strongs": "G2309",
      "translation": "He wants",
      "metadata": {},
      "gematria": {
        "standard": 59,
        "ordinal": 38,
        "reduced": 5
      }
    },
    {
      "position": 9,
      "text": "σκληρύνει.",
      "lemma": [
        "G4645"
      ],
      "morph": "robinson:V-PAI-3S",
      "strongs": "G4645",
      "translation": "He hardens.",
      "metadata": {},
      "gematria": {
        "standard": 823,
        "ordinal": 110,
        "reduced": 4
      }
    }
  ],
  "gematria": {
    "standard": 1867,
    "ordinal": 353,
    "reduced": 40
  }
}