{
  "text": "καὶ τὴν αὐλὴν τὴν ἔξωθεν τοῦ ναοῦ ἔκβαλε ἔξωθεν, καὶ μὴ αὐτὴν μετρήσῃς, ὅτι ἐδόθη τοῖς ἔθνεσιν· καὶ τὴν πόλιν τὴν ἁγίαν πατήσουσιν μῆνας τεσσεράκοντα καὶ δύο.",
  "words": [
    {
      "position": 1,
      "text": "καὶ",
      "lemma": "καί",
      "morph": "robinson:CONJ",
      "strongs": [
        "G2532"
      ],
      "translation": "And",
      "metadata": {
        "editions": "NA28+NA27+Tyn+SBL+WH+Treg+TR+Byz",
        "extendedStrongs": "G2532_A",
        "subMeaning": "and",
        "manuscriptType": "NKO",
        "gloss": "and"
      },
      "source": {
        "raw": "Rev.11.2#01=NKO\tκαὶ (kai)\tAnd\tG2532=CONJ\tκαί=and\tNA28+NA27+Tyn+SBL+WH+Treg+TR+Byz\t\t\tY\tand\t#01\tG2532_A\t\t\t\t\t"
      }
    },
    {
      "position": 2,
      "text": "τὴν",
      "lemma": "ὁ",
      "morph": "robinson:T-ASF",
      "strongs": [
        "G3588"
      ],
      "translation": "the",
      "metadata": {
        "editions": "NA28+NA27+Tyn+SBL+WH+Treg+TR+Byz",
        "extendedStrongs": "G3588_A",
        "subMeaning": "the",
        "manuscriptType": "NKO",
        "gloss": "the/this/who"
      },
      "source": {
        "raw": "Rev.11.2#02=NKO\tτὴν (tēn)\tthe\tG3588=T-ASF\tὁ=the/this/who\tNA28+NA27+Tyn+SBL+WH+Treg+TR+Byz\t\t\tel\tthe\t#02»03:G0833\tG3588_A\t\t\t\t\t"
      }
    },
    {
      "position": 3,
      "text": "αὐλὴν",
      "lemma": "αὐλή",
      "morph": "robinson:N-ASF",
      "strongs": [
        "G0833"
      ],
      "translation": "courtyard",
      "metadata": {
        "editions": "NA28+NA27+Tyn+SBL+WH+Treg+TR+Byz",
        "extendedStrongs": "G0833",
        "subMeaning": "courtyard",
        "manuscriptType": "NKO",
        "gloss": "palace/courtyard"
      },
      "source": {
        "raw": "Rev.11.2#03=NKO\tαὐλὴν (aulēn)\tcourtyard\tG0833=N-ASF\tαὐλή=palace/courtyard\tNA28+NA27+Tyn+SBL+WH+Treg+TR+Byz\t\t\tpatio\tcourtyard\t#03\tG0833\t\t\t\t\t"
      }
    },
    {
      "position": 4,
      "text": "τὴν",
      "lemma": "ὁ",
      "morph": "robinson:T-ASF",
      "strongs": [
        "G3588"
      ],
      "translation": "<the>",
      "metadata": {
        "editions": "NA28+NA27+Tyn+SBL+WH+Treg+TR+Byz",
        "extendedStrongs": "G3588_B",
        "subMeaning": "the",
        "manuscriptType": "NKO",
        "gloss": "the/this/who"
      },
      "source": {
        "raw": "Rev.11.2#04=NKO\tτὴν (tēn)\t<the>\tG3588=T-ASF\tὁ=the/this/who\tNA28+NA27+Tyn+SBL+WH+Treg+TR+Byz\t\t\tel\tthe\t#04»05:G1855\tG3588_B\t\t\t\t\t"
      }
    },
    {
      "position": 5,
      "text": "ἔξωθεν",
      "lemma": "ἔξωθεν",
      "morph": "robinson:PREP",
      "strongs": [
        "G1855"
      ],
      "translation": "outside",
      "metadata": {
        "editions": "NA28+NA27+Tyn+SBL+WH+Treg+Byz+KJV",
        "extendedStrongs": "G1855_A",
        "subMeaning": "outside",
        "variants": "ἔσωθεν (O=esōthen) within - G2081=ADV in: TR",
        "manuscriptType": "NK(O)",
        "gloss": "outside"
      },
      "source": {
        "raw": "Rev.11.2#05=NK(O)\tἔξωθεν (exōthen)\toutside\tG1855=PREP\tἔξωθεν=outside\tNA28+NA27+Tyn+SBL+WH+Treg+Byz+KJV\tἔσωθεν (O=esōthen) within - G2081=ADV in: TR\t\texterior\toutside\t#05\tG1855_A\tG2081\tv ἔσωθεν  (<i>esōthen</i>) 'within' occurs in a few manuscripts (TR) instead of ἔξωθεν  (<i>exōthen</i>) 'outside' in older manuscripts (NA28+NA27+Tyn+SBL+WH+Treg+Byz+KJV)\t\t\t"
      }
    },
    {
      "position": 6,
      "text": "τοῦ",
      "lemma": "ὁ",
      "morph": "robinson:T-GSM",
      "strongs": [
        "G3588"
      ],
      "translation": "the",
      "metadata": {
        "editions": "NA28+NA27+Tyn+SBL+WH+Treg+TR+Byz",
        "extendedStrongs": "G3588_C",
        "subMeaning": "the",
        "manuscriptType": "NKO",
        "gloss": "the/this/who"
      },
      "source": {
        "raw": "Rev.11.2#06=NKO\tτοῦ (tou)\tthe\tG3588=T-GSM\tὁ=the/this/who\tNA28+NA27+Tyn+SBL+WH+Treg+TR+Byz\t\t\tde la\tthe\t#06»07:G3485\tG3588_C\t\t\t\t\t"
      }
    },
    {
      "position": 7,
      "text": "ναοῦ",
      "lemma": "ναός",
      "morph": "robinson:N-GSM",
      "strongs": [
        "G3485"
      ],
      "translation": "temple",
      "metadata": {
        "editions": "NA28+NA27+Tyn+SBL+WH+Treg+TR+Byz",
        "extendedStrongs": "G3485",
        "subMeaning": "temple",
        "manuscriptType": "NKO",
        "gloss": "temple"
      },
      "source": {
        "raw": "Rev.11.2#07=NKO\tναοῦ (naou)\ttemple\tG3485=N-GSM\tναός=temple\tNA28+NA27+Tyn+SBL+WH+Treg+TR+Byz\t\t\thabitación divina\ttemple\t#07\tG3485\t\t\t\t\t"
      }
    },
    {
      "position": 8,
      "text": "ἔκβαλε",
      "lemma": "ἐκβάλλω",
      "morph": "robinson:V-2AAM-2S",
      "strongs": [
        "G1544"
      ],
      "translation": "do leave",
      "metadata": {
        "editions": "NA28+NA27+Tyn+SBL+WH+Treg+TR+Byz",
        "extendedStrongs": "G1544",
        "subMeaning": "to expel",
        "manuscriptType": "NKO",
        "gloss": "to expel"
      },
      "source": {
        "raw": "Rev.11.2#08=NKO\tἔκβαλε (ekbale)\tdo leave\tG1544=V-2AAM-2S\tἐκβάλλω=to expel\tNA28+NA27+Tyn+SBL+WH+Treg+TR+Byz\t\t\tarroja hacia fuera\tto expel\t#08\tG1544\t\t\t\t\t"
      }
    },
    {
      "position": 9,
      "text": "ἔξωθεν,",
      "lemma": "ἔξωθεν",
      "morph": "robinson:PREP",
      "strongs": [
        "G1855"
      ],
      "translation": "outside,",
      "metadata": {
        "editions": "NA28+NA27+Tyn+SBL+WH+Treg",
        "extendedStrongs": "G1855_b",
        "subMeaning": "outside",
        "variants": "ἔξω (t=exō) outer - G1854=PREP in: TR+Byz",
        "manuscriptType": "N(k)O",
        "gloss": "outside"
      },
      "source": {
        "raw": "Rev.11.2#09=N(k)O\tἔξωθεν, (exōthen)\toutside,\tG1855=PREP\tἔξωθεν=outside\tNA28+NA27+Tyn+SBL+WH+Treg\tἔξω (t=exō) outer - G1854=PREP in: TR+Byz\t\tafuera\toutside\t#09\tG1855_b\tG1854\t\t\t\t"
      }
    },
    {
      "position": 10,
      "text": "καὶ",
      "lemma": "καί",
      "morph": "robinson:CONJ",
      "strongs": [
        "G2532"
      ],
      "translation": "and",
      "metadata": {
        "editions": "NA28+NA27+Tyn+SBL+WH+Treg+TR+Byz",
        "extendedStrongs": "G2532_B",
        "subMeaning": "and",
        "manuscriptType": "NKO",
        "gloss": "and"
      },
      "source": {
        "raw": "Rev.11.2#10=NKO\tκαὶ (kai)\tand\tG2532=CONJ\tκαί=and\tNA28+NA27+Tyn+SBL+WH+Treg+TR+Byz\t\t\ty\tand\t#10\tG2532_B\t\t\t\t\t"
      }
    },
    {
      "position": 11,
      "text": "μὴ",
      "lemma": "μή",
      "morph": "robinson:PRT-N",
      "strongs": [
        "G3361"
      ],
      "translation": "not",
      "metadata": {
        "editions": "NA28+NA27+Tyn+SBL+WH+Treg+TR+Byz",
        "extendedStrongs": "G3361",
        "subMeaning": "not",
        "manuscriptType": "NKO",
        "gloss": "not"
      },
      "source": {
        "raw": "Rev.11.2#11=NKO\tμὴ (mē)\tnot\tG3361=PRT-N\tμή=not\tNA28+NA27+Tyn+SBL+WH+Treg+TR+Byz\t\t\tno\tnot\t#11»13:G3354\tG3361\t\t\t\t\t"
      }
    },
    {
      "position": 12,
      "text": "αὐτὴν",
      "lemma": "αὐτός",
      "morph": "robinson:P-ASF",
      "strongs": [
        "G0846"
      ],
      "translation": "it",
      "metadata": {
        "editions": "NA28+NA27+Tyn+SBL+WH+Treg+TR+Byz",
        "extendedStrongs": "G0846",
        "subMeaning": "her",
        "manuscriptType": "NKO",
        "gloss": "he/she/it/self"
      },
      "source": {
        "raw": "Rev.11.2#12=NKO\tαὐτὴν (autēn)\tit\tG0846=P-ASF\tαὐτός=he/she/it/self\tNA28+NA27+Tyn+SBL+WH+Treg+TR+Byz\t\t\ta él\ther\t#12»13:G3354\tG0846\tG3778\t\t\t\t"
      }
    },
    {
      "position": 13,
      "text": "μετρήσῃς,",
      "lemma": "μετρέω",
      "morph": "robinson:V-AAS-2S",
      "strongs": [
        "G3354"
      ],
      "translation": "may measure,",
      "metadata": {
        "editions": "NA28+NA27+Tyn+SBL+WH+Treg+TR+Byz",
        "extendedStrongs": "G3354",
        "subMeaning": "to measure",
        "manuscriptType": "NKO",
        "gloss": "to measure"
      },
      "source": {
        "raw": "Rev.11.2#13=NKO\tμετρήσῃς, (metrēsēs)\tmay measure,\tG3354=V-AAS-2S\tμετρέω=to measure\tNA28+NA27+Tyn+SBL+WH+Treg+TR+Byz\t\t\tmidas\tto measure\t#13\tG3354\t\t\t\t\t"
      }
    },
    {
      "position": 14,
      "text": "ὅτι",
      "lemma": "ὅτι",
      "morph": "robinson:CONJ",
      "strongs": [
        "G3754H"
      ],
      "translation": "because",
      "metadata": {
        "editions": "NA28+NA27+Tyn+SBL+WH+Treg+TR+Byz",
        "extendedStrongs": "G3754",
        "subMeaning": ": since»that/since|2_since",
        "manuscriptType": "NKO",
        "gloss": "that/since"
      },
      "source": {
        "raw": "Rev.11.2#14=NKO\tὅτι (hoti)\tbecause\tG3754H=CONJ\tὅτι=that/since\tNA28+NA27+Tyn+SBL+WH+Treg+TR+Byz\t\t\tporque\t: since»that/since|2_since\t#14\tG3754\t\t\t\t\t"
      }
    },
    {
      "position": 15,
      "text": "ἐδόθη",
      "lemma": "δίδωμι",
      "morph": "robinson:V-API-3S",
      "strongs": [
        "G1325"
      ],
      "translation": "it has been given [up]",
      "metadata": {
        "editions": "NA28+NA27+Tyn+SBL+WH+Treg+TR+Byz",
        "extendedStrongs": "G1325",
        "subMeaning": "to give",
        "manuscriptType": "NKO",
        "gloss": "to give"
      },
      "source": {
        "raw": "Rev.11.2#15=NKO\tἐδόθη (edothē)\tit has been given [up]\tG1325=V-API-3S\tδίδωμι=to give\tNA28+NA27+Tyn+SBL+WH+Treg+TR+Byz\t\t\tfue dado\tto give\t#15\tG1325\t\t\t\t\t"
      }
    },
    {
      "position": 16,
      "text": "τοῖς",
      "lemma": "ὁ",
      "morph": "robinson:T-DPN",
      "strongs": [
        "G3588"
      ],
      "translation": "to the",
      "metadata": {
        "editions": "NA28+NA27+Tyn+SBL+WH+Treg+TR+Byz",
        "extendedStrongs": "G3588_D",
        "subMeaning": "the",
        "manuscriptType": "NKO",
        "gloss": "the/this/who"
      },
      "source": {
        "raw": "Rev.11.2#16=NKO\tτοῖς (tois)\tto the\tG3588=T-DPN\tὁ=the/this/who\tNA28+NA27+Tyn+SBL+WH+Treg+TR+Byz\t\t\ta las\tthe\t#16»17:G1484\tG3588_D\t\t\t\t\t"
      }
    },
    {
      "position": 17,
      "text": "ἔθνεσιν·",
      "lemma": "ἔθνος",
      "morph": "robinson:N-DPN",
      "strongs": [
        "G1484"
      ],
      "translation": "nations;",
      "metadata": {
        "editions": "NA28+NA27+Tyn+SBL+WH+Treg+TR+Byz",
        "extendedStrongs": "G1484",
        "subMeaning": "Gentiles»Gentile@Gen.10.5",
        "manuscriptType": "NKO",
        "gloss": "Gentile nation"
      },
      "source": {
        "raw": "Rev.11.2#17=NKO\tἔθνεσιν· (ethnesin)\tnations;\tG1484=N-DPN\tἔθνος=Gentile nation\tNA28+NA27+Tyn+SBL+WH+Treg+TR+Byz\t\t\tnaciones\tGentiles»Gentile@Gen.10.5\t#17\tG1484\t\t\t\t\t"
      }
    },
    {
      "position": 18,
      "text": "καὶ",
      "lemma": "καί",
      "morph": "robinson:CONJ",
      "strongs": [
        "G2532"
      ],
      "translation": "and",
      "metadata": {
        "editions": "NA28+NA27+Tyn+SBL+WH+Treg+TR+Byz",
        "extendedStrongs": "G2532_C",
        "subMeaning": "and",
        "manuscriptType": "NKO",
        "gloss": "and"
      },
      "source": {
        "raw": "Rev.11.2#18=NKO\tκαὶ (kai)\tand\tG2532=CONJ\tκαί=and\tNA28+NA27+Tyn+SBL+WH+Treg+TR+Byz\t\t\ty\tand\t#18\tG2532_C\t\t\t\t\t"
      }
    },
    {
      "position": 19,
      "text": "τὴν",
      "lemma": "ὁ",
      "morph": "robinson:T-ASF",
      "strongs": [
        "G3588"
      ],
      "translation": "the",
      "metadata": {
        "editions": "NA28+NA27+Tyn+SBL+WH+Treg+TR+Byz",
        "extendedStrongs": "G3588_E",
        "subMeaning": "the",
        "manuscriptType": "NKO",
        "gloss": "the/this/who"
      },
      "source": {
        "raw": "Rev.11.2#19=NKO\tτὴν (tēn)\tthe\tG3588=T-ASF\tὁ=the/this/who\tNA28+NA27+Tyn+SBL+WH+Treg+TR+Byz\t\t\ta la\tthe\t#19»20:G4172\tG3588_E\t\t\t\t\t"
      }
    },
    {
      "position": 20,
      "text": "πόλιν",
      "lemma": "πόλις",
      "morph": "robinson:N-ASF",
      "strongs": [
        "G4172"
      ],
      "translation": "city",
      "metadata": {
        "editions": "NA28+NA27+Tyn+SBL+WH+Treg+TR+Byz",
        "extendedStrongs": "G4172",
        "subMeaning": "city",
        "manuscriptType": "NKO",
        "gloss": "city"
      },
      "source": {
        "raw": "Rev.11.2#20=NKO\tπόλιν (polin)\tcity\tG4172=N-ASF\tπόλις=city\tNA28+NA27+Tyn+SBL+WH+Treg+TR+Byz\t\t\tciudad\tcity\t#20\tG4172\t\t\t\t\t"
      }
    },
    {
      "position": 21,
      "text": "τὴν",
      "lemma": "ὁ",
      "morph": "robinson:T-ASF",
      "strongs": [
        "G3588"
      ],
      "translation": "<the>",
      "metadata": {
        "editions": "NA28+NA27+Tyn+SBL+WH+Treg+TR+Byz",
        "extendedStrongs": "G3588_F",
        "subMeaning": "the",
        "manuscriptType": "NKO",
        "gloss": "the/this/who"
      },
      "source": {
        "raw": "Rev.11.2#21=NKO\tτὴν (tēn)\t<the>\tG3588=T-ASF\tὁ=the/this/who\tNA28+NA27+Tyn+SBL+WH+Treg+TR+Byz\t\t\tla\tthe\t#21»22:G0040\tG3588_F\t\t\t\t\t"
      }
    },
    {
      "position": 22,
      "text": "ἁγίαν",
      "lemma": "ἅγιος",
      "morph": "robinson:A-ASF",
      "strongs": [
        "G0040G"
      ],
      "translation": "holy",
      "metadata": {
        "editions": "NA28+NA27+Tyn+SBL+WH+Treg+TR+Byz",
        "extendedStrongs": "G0040",
        "subMeaning": ": holy»holy|1_holy",
        "manuscriptType": "NKO",
        "gloss": "holy"
      },
      "source": {
        "raw": "Rev.11.2#22=NKO\tἁγίαν (hagian)\tholy\tG0040G=A-ASF\tἅγιος=holy\tNA28+NA27+Tyn+SBL+WH+Treg+TR+Byz\t\t\tsanta\t: holy»holy|1_holy\t#22\tG0040\tG0039\t\t\t\t"
      }
    },
    {
      "position": 23,
      "text": "πατήσουσιν",
      "lemma": "πατέω",
      "morph": "robinson:V-FAI-3P",
      "strongs": [
        "G3961"
      ],
      "translation": "they will trample upon",
      "metadata": {
        "editions": "NA28+NA27+Tyn+SBL+WH+Treg+TR+Byz",
        "extendedStrongs": "G3961",
        "subMeaning": "to trample",
        "manuscriptType": "NKO",
        "gloss": "to trample"
      },
      "source": {
        "raw": "Rev.11.2#23=NKO\tπατήσουσιν (patēsousin)\tthey will trample upon\tG3961=V-FAI-3P\tπατέω=to trample\tNA28+NA27+Tyn+SBL+WH+Treg+TR+Byz\t\t\thollarán\tto trample\t#23\tG3961\t\t\t\t\t"
      }
    },
    {
      "position": 24,
      "text": "μῆνας",
      "lemma": "μήν",
      "morph": "robinson:N-APM",
      "strongs": [
        "G3376"
      ],
      "translation": "months",
      "metadata": {
        "editions": "NA28+NA27+Tyn+SBL+WH+Treg+TR+Byz",
        "extendedStrongs": "G3376",
        "subMeaning": "month",
        "manuscriptType": "NKO",
        "gloss": "month"
      },
      "source": {
        "raw": "Rev.11.2#24=NKO\tμῆνας (mēnas)\tmonths\tG3376=N-APM\tμήν=month\tNA28+NA27+Tyn+SBL+WH+Treg+TR+Byz\t\t\tmeses\tmonth\t#24\tG3376\t\t\t\t\t"
      }
    },
    {
      "position": 25,
      "text": "τεσσεράκοντα",
      "lemma": "τεσσαράκοντα",
      "morph": "robinson:A-NUI",
      "strongs": [
        "G5062"
      ],
      "translation": "forty",
      "metadata": {
        "editions": "NA28+NA27+Tyn+SBL+WH+Treg+TR+Byz",
        "extendedStrongs": "G5062",
        "subMeaning": "forty",
        "variants": "TR: τεσσαράκοντα ;",
        "manuscriptType": "NKO",
        "gloss": "forty"
      },
      "source": {
        "raw": "Rev.11.2#25=NKO\tτεσσεράκοντα (tesserakonta)\tforty\tG5062=A-NUI\tτεσσαράκοντα=forty\tNA28+NA27+Tyn+SBL+WH+Treg+TR+Byz\t\tTR: τεσσαράκοντα ; \tcuarenta\tforty\t#25\tG5062\t\t\t\t\t"
      }
    },
    {
      "position": 26,
      "text": "καὶ",
      "lemma": "καί",
      "morph": "robinson:CONJ",
      "strongs": [
        "G2532"
      ],
      "translation": "and",
      "metadata": {
        "editions": "NA28+NA27+WH+Byz+KJV",
        "extendedStrongs": "G2532_D",
        "subMeaning": "and",
        "manuscriptType": "NKO",
        "gloss": "and"
      },
      "source": {
        "raw": "Rev.11.2#26=NKO\tκαὶ (kai)\tand\tG2532=CONJ\tκαί=and\tNA28+NA27+WH+Byz+KJV\t\t\ty\tand\t#26\tG2532_D\t\t\t\t\t"
      }
    },
    {
      "position": 27,
      "text": "δύο.",
      "lemma": "δύο",
      "morph": "robinson:A-NUI",
      "strongs": [
        "G1417"
      ],
      "translation": "two.",
      "metadata": {
        "editions": "NA28+NA27+Tyn+SBL+WH+Treg+TR+Byz",
        "extendedStrongs": "G1417",
        "subMeaning": "two",
        "manuscriptType": "NKO",
        "gloss": "two"
      },
      "source": {
        "raw": "Rev.11.2#27=NKO\tδύο.¶ (duo)\ttwo.\tG1417=A-NUI\tδύο=two\tNA28+NA27+Tyn+SBL+WH+Treg+TR+Byz\t\t\tdos\ttwo\t#27\tG1417\t\t\t\t\t"
      }
    }
  ]
}