{
  "text": "Τοῦ δὲ Ἰησοῦ γεννηθέντος ἐν Βηθλέεμ τῆς Ἰουδαίας ἐν ἡμέραις Ἡρῴδου τοῦ βασιλέως ἰδοὺ μάγοι ἀπὸ ἀνατολῶν παρεγένοντο εἰς Ἱεροσόλυμα",
  "words": [
    {
      "position": 1,
      "text": "Τοῦ",
      "lemma": [
        "G3588"
      ],
      "morph": "robinson:T-GSM",
      "strongs": "G3588",
      "translation": "<the>",
      "metadata": {},
      "gematria": {
        "standard": 770,
        "ordinal": 54,
        "reduced": 5
      }
    },
    {
      "position": 2,
      "text": "δὲ",
      "lemma": [
        "G1161"
      ],
      "morph": "robinson:CONJ",
      "strongs": "G1161",
      "translation": "Now",
      "metadata": {},
      "gematria": {
        "standard": 9,
        "ordinal": 9,
        "reduced": 9
      }
    },
    {
      "position": 3,
      "text": "Ἰησοῦ",
      "lemma": [
        "G2424G"
      ],
      "morph": "robinson:N-GSM-P",
      "strongs": "G2424G",
      "translation": "Jesus",
      "metadata": {},
      "gematria": {
        "standard": 688,
        "ordinal": 69,
        "reduced": 4
      }
    },
    {
      "position": 4,
      "text": "γεννηθέντος",
      "lemma": [
        "G1080"
      ],
      "morph": "robinson:V-APP-GSM",
      "strongs": "G1080",
      "translation": "having been born",
      "metadata": {},
      "gematria": {
        "standard": 750,
        "ordinal": 119,
        "reduced": 3
      }
    },
    {
      "position": 5,
      "text": "ἐν",
      "lemma": [
        "G1722"
      ],
      "morph": "robinson:PREP",
      "strongs": "G1722",
      "translation": "in",
      "metadata": {},
      "gematria": {
        "standard": 55,
        "ordinal": 18,
        "reduced": 1
      }
    },
    {
      "position": 6,
      "text": "Βηθλέεμ",
      "lemma": [
        "G0965"
      ],
      "morph": "robinson:N-DSF-L",
      "strongs": "G0965",
      "translation": "Bethlehem",
      "metadata": {},
      "gematria": {
        "standard": 99,
        "ordinal": 50,
        "reduced": 9
      }
    },
    {
      "position": 7,
      "text": "τῆς",
      "lemma": [
        "G3588"
      ],
      "morph": "robinson:T-GSF",
      "strongs": "G3588",
      "translation": "<the>",
      "metadata": {},
      "gematria": {
        "standard": 508,
        "ordinal": 44,
        "reduced": 4
      }
    },
    {
      "position": 8,
      "text": "Ἰουδαίας",
      "lemma": [
        "G2449"
      ],
      "morph": "robinson:N-GSF-L",
      "strongs": "G2449",
      "translation": "of Judea",
      "metadata": {},
      "gematria": {
        "standard": 696,
        "ordinal": 77,
        "reduced": 3
      }
    },
    {
      "position": 9,
      "text": "ἐν",
      "lemma": [
        "G1722"
      ],
      "morph": "robinson:PREP",
      "strongs": "G1722",
      "translation": "in",
      "metadata": {},
      "gematria": {
        "standard": 55,
        "ordinal": 18,
        "reduced": 1
      }
    },
    {
      "position": 10,
      "text": "ἡμέραις",
      "lemma": [
        "G2250"
      ],
      "morph": "robinson:N-DPF",
      "strongs": "G2250",
      "translation": "[the] days",
      "metadata": {},
      "gematria": {
        "standard": 364,
        "ordinal": 69,
        "reduced": 4
      }
    },
    {
      "position": 11,
      "text": "Ἡρῴδου",
      "lemma": [
        "G2264G"
      ],
      "morph": "robinson:N-GSM-P",
      "strongs": "G2264G",
      "translation": "of Herod",
      "metadata": {},
      "gematria": {
        "standard": 1392,
        "ordinal": 96,
        "reduced": 6
      }
    },
    {
      "position": 12,
      "text": "τοῦ",
      "lemma": [
        "G3588"
      ],
      "morph": "robinson:T-GSM",
      "strongs": "G3588",
      "translation": "the",
      "metadata": {},
      "gematria": {
        "standard": 770,
        "ordinal": 54,
        "reduced": 5
      }
    },
    {
      "position": 13,
      "text": "βασιλέως",
      "lemma": [
        "G0935"
      ],
      "morph": "robinson:N-GSM",
      "strongs": "G0935",
      "translation": "king",
      "metadata": {},
      "gematria": {
        "standard": 1248,
        "ordinal": 88,
        "reduced": 6
      }
    },
    {
      "position": 14,
      "text": "ἰδοὺ",
      "lemma": [
        "G2400"
      ],
      "morph": "robinson:INJ",
      "strongs": "G2400",
      "translation": "behold",
      "metadata": {},
      "gematria": {
        "standard": 484,
        "ordinal": 48,
        "reduced": 7
      }
    },
    {
      "position": 15,
      "text": "μάγοι",
      "lemma": [
        "G3097"
      ],
      "morph": "robinson:N-NPM",
      "strongs": "G3097",
      "translation": "Magi",
      "metadata": {},
      "gematria": {
        "standard": 124,
        "ordinal": 40,
        "reduced": 7
      }
    },
    {
      "position": 16,
      "text": "ἀπὸ",
      "lemma": [
        "G0575"
      ],
      "morph": "robinson:PREP",
      "strongs": "G0575",
      "translation": "from [the]",
      "metadata": {},
      "gematria": {
        "standard": 151,
        "ordinal": 32,
        "reduced": 7
      }
    },
    {
      "position": 17,
      "text": "ἀνατολῶν",
      "lemma": [
        "G0395"
      ],
      "morph": "robinson:N-GPF",
      "strongs": "G0395",
      "translation": "east",
      "metadata": {},
      "gematria": {
        "standard": 1302,
        "ordinal": 97,
        "reduced": 6
      }
    },
    {
      "position": 18,
      "text": "παρεγένοντο",
      "lemma": [
        "G3854"
      ],
      "morph": "robinson:V-2ADI-3P",
      "strongs": "G3854",
      "translation": "arrived",
      "metadata": {},
      "gematria": {
        "standard": 734,
        "ordinal": 122,
        "reduced": 5
      }
    },
    {
      "position": 19,
      "text": "εἰς",
      "lemma": [
        "G1519"
      ],
      "morph": "robinson:PREP",
      "strongs": "G1519",
      "translation": "in",
      "metadata": {},
      "gematria": {
        "standard": 215,
        "ordinal": 32,
        "reduced": 8
      }
    },
    {
      "position": 20,
      "text": "Ἱεροσόλυμα",
      "lemma": [
        "G2414"
      ],
      "morph": "robinson:N-APN-L",
      "strongs": "G2414",
      "translation": "Jerusalem",
      "metadata": {},
      "gematria": {
        "standard": 926,
        "ordinal": 123,
        "reduced": 8
      }
    }
  ],
  "gematria": {
    "standard": 11340,
    "ordinal": 1259,
    "reduced": 108
  }
}