{
  "text": "ἴδετε τὰς χεῖράς μου καὶ τοὺς πόδας μου ὅτι ἐγώ εἰμι αὐτός· ψηλαφήσατέ με καὶ ἴδετε ὅτι πνεῦμα σάρκα καὶ ὀστέα οὐκ ἔχει καθὼς ἐμὲ θεωρεῖτε ἔχοντα.",
  "words": [
    {
      "position": 1,
      "text": "ἴδετε",
      "lemma": "εἴδω",
      "morph": "robinson:V-2AAM-2P",
      "strongs": [
        "G1492H"
      ],
      "translation": "do see",
      "metadata": {
        "editions": "NA28+NA27+Tyn+SBL+WH+Treg+TR+Byz",
        "extendedStrongs": "G1492_A",
        "subMeaning": ": see»to perceive|2_see",
        "manuscriptType": "NKO",
        "gloss": "to perceive"
      },
      "source": {
        "raw": "Luk.24.39#01=NKO\tἴδετε (idete)\tdo see\tG1492H=V-2AAM-2P\tεἴδω=to perceive\tNA28+NA27+Tyn+SBL+WH+Treg+TR+Byz\t\t\tVean\t: see»to perceive|2_see\t#01\tG1492_A\t\t\t\t\t"
      }
    },
    {
      "position": 2,
      "text": "τὰς",
      "lemma": "ὁ",
      "morph": "robinson:T-APF",
      "strongs": [
        "G3588"
      ],
      "translation": "the",
      "metadata": {
        "editions": "NA28+NA27+Tyn+SBL+WH+Treg+TR+Byz",
        "extendedStrongs": "G3588_A",
        "subMeaning": "the",
        "manuscriptType": "NKO",
        "gloss": "the/this/who"
      },
      "source": {
        "raw": "Luk.24.39#02=NKO\tτὰς (tas)\tthe\tG3588=T-APF\tὁ=the/this/who\tNA28+NA27+Tyn+SBL+WH+Treg+TR+Byz\t\t\tlas\tthe\t#02»03:G5495\tG3588_A\t\t\t\t\t"
      }
    },
    {
      "position": 3,
      "text": "χεῖράς",
      "lemma": "χείρ",
      "morph": "robinson:N-APF",
      "strongs": [
        "G5495"
      ],
      "translation": "hands",
      "metadata": {
        "editions": "NA28+NA27+Tyn+SBL+WH+Treg+TR+Byz",
        "extendedStrongs": "G5495",
        "subMeaning": "hands",
        "manuscriptType": "NKO",
        "gloss": "hand"
      },
      "source": {
        "raw": "Luk.24.39#03=NKO\tχεῖράς (cheiras)\thands\tG5495=N-APF\tχείρ=hand\tNA28+NA27+Tyn+SBL+WH+Treg+TR+Byz\t\t\tmanos\thands\t#03\tG5495\t\t\t\t\t"
      }
    },
    {
      "position": 4,
      "text": "μου",
      "lemma": "ἐγώ",
      "morph": "robinson:P-1GS",
      "strongs": [
        "G3165"
      ],
      "translation": "of Me",
      "metadata": {
        "editions": "NA28+NA27+Tyn+SBL+WH+Treg+TR+Byz",
        "extendedStrongs": "G3165_A",
        "subMeaning": "my",
        "manuscriptType": "NKO",
        "gloss": "I/we"
      },
      "source": {
        "raw": "Luk.24.39#04=NKO\tμου (mou)\tof Me\tG3165=P-1GS\tἐγώ=I/we\tNA28+NA27+Tyn+SBL+WH+Treg+TR+Byz\t\t\tmías\tmy\t#04«03:G5495\tG3165_A\tG3450\t\t\t\t"
      }
    },
    {
      "position": 5,
      "text": "καὶ",
      "lemma": "καί",
      "morph": "robinson:CONJ",
      "strongs": [
        "G2532"
      ],
      "translation": "and",
      "metadata": {
        "editions": "NA28+NA27+Tyn+SBL+WH+Treg+TR+Byz",
        "extendedStrongs": "G2532_A",
        "subMeaning": "and",
        "manuscriptType": "NKO",
        "gloss": "and"
      },
      "source": {
        "raw": "Luk.24.39#05=NKO\tκαὶ (kai)\tand\tG2532=CONJ\tκαί=and\tNA28+NA27+Tyn+SBL+WH+Treg+TR+Byz\t\t\ty\tand\t#05\tG2532_A\t\t\t\t\t"
      }
    },
    {
      "position": 6,
      "text": "τοὺς",
      "lemma": "ὁ",
      "morph": "robinson:T-APM",
      "strongs": [
        "G3588"
      ],
      "translation": "the",
      "metadata": {
        "editions": "NA28+NA27+Tyn+SBL+WH+Treg+TR+Byz",
        "extendedStrongs": "G3588_B",
        "subMeaning": "the",
        "manuscriptType": "NKO",
        "gloss": "the/this/who"
      },
      "source": {
        "raw": "Luk.24.39#06=NKO\tτοὺς (tous)\tthe\tG3588=T-APM\tὁ=the/this/who\tNA28+NA27+Tyn+SBL+WH+Treg+TR+Byz\t\t\tlos\tthe\t#06»07:G4228\tG3588_B\t\t\t\t\t"
      }
    },
    {
      "position": 7,
      "text": "πόδας",
      "lemma": "πούς",
      "morph": "robinson:N-APM",
      "strongs": [
        "G4228"
      ],
      "translation": "feet",
      "metadata": {
        "editions": "NA28+NA27+Tyn+SBL+WH+Treg+TR+Byz",
        "extendedStrongs": "G4228",
        "subMeaning": "foot",
        "manuscriptType": "NKO",
        "gloss": "foot"
      },
      "source": {
        "raw": "Luk.24.39#07=NKO\tπόδας (podas)\tfeet\tG4228=N-APM\tπούς=foot\tNA28+NA27+Tyn+SBL+WH+Treg+TR+Byz\t\t\tpies\tfoot\t#07\tG4228\t\t\t\t\t"
      }
    },
    {
      "position": 8,
      "text": "μου",
      "lemma": "ἐγώ",
      "morph": "robinson:P-1GS",
      "strongs": [
        "G3165"
      ],
      "translation": "of Me",
      "metadata": {
        "editions": "NA28+NA27+Tyn+SBL+WH+Treg+TR+Byz",
        "extendedStrongs": "G3165_B",
        "subMeaning": "my",
        "manuscriptType": "NKO",
        "gloss": "I/we"
      },
      "source": {
        "raw": "Luk.24.39#08=NKO\tμου (mou)\tof Me\tG3165=P-1GS\tἐγώ=I/we\tNA28+NA27+Tyn+SBL+WH+Treg+TR+Byz\t\t\tmíos\tmy\t#08«07:G4228\tG3165_B\tG3450\t\t\t\t"
      }
    },
    {
      "position": 9,
      "text": "ὅτι",
      "lemma": "ὅτι",
      "morph": "robinson:CONJ",
      "strongs": [
        "G3754G"
      ],
      "translation": "that",
      "metadata": {
        "editions": "NA28+NA27+Tyn+SBL+WH+Treg+TR+Byz",
        "extendedStrongs": "G3754_A",
        "subMeaning": ": that»that/since|1_that",
        "manuscriptType": "NKO",
        "gloss": "that/since"
      },
      "source": {
        "raw": "Luk.24.39#09=NKO\tὅτι (hoti)\tthat\tG3754G=CONJ\tὅτι=that/since\tNA28+NA27+Tyn+SBL+WH+Treg+TR+Byz\t\t\tque\t: that»that/since|1_that\t#09«01:G1492\tG3754_A\t\t\t\t\t"
      }
    },
    {
      "position": 10,
      "text": "ἐγώ",
      "lemma": "ἐγώ",
      "morph": "robinson:P-1NS",
      "strongs": [
        "G1473"
      ],
      "translation": "I myself",
      "metadata": {
        "editions": "NA28+NA27+Tyn+SBL+WH+Treg+TR+Byz",
        "extendedStrongs": "G1473_A",
        "subMeaning": "I",
        "manuscriptType": "NKO",
        "gloss": "I/we"
      },
      "source": {
        "raw": "Luk.24.39#10=NKO\tἐγώ (egō)\tI myself\tG1473=P-1NS\tἐγώ=I/we\tNA28+NA27+Tyn+SBL+WH+Treg+TR+Byz\t\t\tyo\tI\t#10»11:G1510\tG1473_A\t\t\t\t\t"
      }
    },
    {
      "position": 11,
      "text": "εἰμι",
      "lemma": "εἰμί",
      "morph": "robinson:V-PAI-1S",
      "strongs": [
        "G1510"
      ],
      "translation": "am",
      "metadata": {
        "editions": "NA28+NA27+Tyn+SBL+WH+Treg+TR+Byz",
        "extendedStrongs": "G1510",
        "subMeaning": "to be",
        "manuscriptType": "NKO",
        "gloss": "to be"
      },
      "source": {
        "raw": "Luk.24.39#11=NKO\tεἰμι (eimi)\tam\tG1510=V-PAI-1S\tεἰμί=to be\tNA28+NA27+Tyn+SBL+WH+Treg+TR+Byz\t\t\testoy siendo\tto be\t#11\tG1510\t\t\t\t\t"
      }
    },
    {
      "position": 12,
      "text": "αὐτός·",
      "lemma": "αὐτός",
      "morph": "robinson:P-NSM",
      "strongs": [
        "G0846"
      ],
      "translation": "He himself;",
      "metadata": {
        "editions": "NA28+NA27+Tyn+SBL+WH+Treg+TR«3+Byz«3",
        "extendedStrongs": "G0846",
        "subMeaning": "he",
        "manuscriptType": "NKO",
        "gloss": "he/she/it/self"
      },
      "source": {
        "raw": "Luk.24.39#12=NKO\tαὐτός· (autos)\tHe himself;\tG0846=P-NSM\tαὐτός=he/she/it/self\tNA28+NA27+Tyn+SBL+WH+Treg+TR«3+Byz«3\t\t\tmismo\the\t#12«11:G1510\tG0846\tG3778\t\t\t\t"
      }
    },
    {
      "position": 13,
      "text": "ψηλαφήσατέ",
      "lemma": "ψηλαφάω",
      "morph": "robinson:V-AAM-2P",
      "strongs": [
        "G5584"
      ],
      "translation": "do touch",
      "metadata": {
        "editions": "NA28+NA27+Tyn+SBL+WH+Treg+TR+Byz",
        "extendedStrongs": "G5584",
        "subMeaning": "to touch",
        "manuscriptType": "NKO",
        "gloss": "to touch"
      },
      "source": {
        "raw": "Luk.24.39#13=NKO\tψηλαφήσατέ (psēlaphēsate)\tdo touch\tG5584=V-AAM-2P\tψηλαφάω=to touch\tNA28+NA27+Tyn+SBL+WH+Treg+TR+Byz\t\t\tpalpen\tto touch\t#13\tG5584\t\t\t\t\t"
      }
    },
    {
      "position": 14,
      "text": "με",
      "lemma": "ἐγώ",
      "morph": "robinson:P-1AS",
      "strongs": [
        "G3165"
      ],
      "translation": "Me",
      "metadata": {
        "editions": "NA28+NA27+Tyn+SBL+WH+Treg+TR+Byz",
        "extendedStrongs": "G3165_C",
        "subMeaning": "me",
        "manuscriptType": "NKO",
        "gloss": "I/we"
      },
      "source": {
        "raw": "Luk.24.39#14=NKO\tμε (me)\tMe\tG3165=P-1AS\tἐγώ=I/we\tNA28+NA27+Tyn+SBL+WH+Treg+TR+Byz\t\t\ta mí\tme\t#14«13:G5584\tG3165_C\t\t\t\t\t"
      }
    },
    {
      "position": 15,
      "text": "καὶ",
      "lemma": "καί",
      "morph": "robinson:CONJ",
      "strongs": [
        "G2532"
      ],
      "translation": "and",
      "metadata": {
        "editions": "NA28+NA27+Tyn+SBL+WH+Treg+TR+Byz",
        "extendedStrongs": "G2532_B",
        "subMeaning": "and",
        "manuscriptType": "NKO",
        "gloss": "and"
      },
      "source": {
        "raw": "Luk.24.39#15=NKO\tκαὶ (kai)\tand\tG2532=CONJ\tκαί=and\tNA28+NA27+Tyn+SBL+WH+Treg+TR+Byz\t\t\ty\tand\t#15\tG2532_B\t\t\t\t\t"
      }
    },
    {
      "position": 16,
      "text": "ἴδετε",
      "lemma": "εἴδω",
      "morph": "robinson:V-2AAM-2P",
      "strongs": [
        "G1492H"
      ],
      "translation": "do see",
      "metadata": {
        "editions": "NA28+NA27+Tyn+SBL+WH+Treg+TR+Byz",
        "extendedStrongs": "G1492_B",
        "subMeaning": ": see»to perceive|2_see",
        "manuscriptType": "NKO",
        "gloss": "to perceive"
      },
      "source": {
        "raw": "Luk.24.39#16=NKO\tἴδετε (idete)\tdo see\tG1492H=V-2AAM-2P\tεἴδω=to perceive\tNA28+NA27+Tyn+SBL+WH+Treg+TR+Byz\t\t\tvean\t: see»to perceive|2_see\t#16\tG1492_B\t\t\t\t\t"
      }
    },
    {
      "position": 17,
      "text": "ὅτι",
      "lemma": "ὅτι",
      "morph": "robinson:CONJ",
      "strongs": [
        "G3754H"
      ],
      "translation": "for",
      "metadata": {
        "editions": "NA28+NA27+Tyn+SBL+WH+Treg+TR+Byz",
        "extendedStrongs": "G3754_B",
        "subMeaning": ": since»that/since|2_since",
        "manuscriptType": "NKO",
        "gloss": "that/since"
      },
      "source": {
        "raw": "Luk.24.39#17=NKO\tὅτι (hoti)\tfor\tG3754H=CONJ\tὅτι=that/since\tNA28+NA27+Tyn+SBL+WH+Treg+TR+Byz\t\t\tque\t: since»that/since|2_since\t#17\tG3754_B\t\t\t\t\t"
      }
    },
    {
      "position": 18,
      "text": "πνεῦμα",
      "lemma": "πνεῦμα",
      "morph": "robinson:N-NSN",
      "strongs": [
        "G4151G"
      ],
      "translation": "a spirit",
      "metadata": {
        "editions": "NA28+NA27+Tyn+SBL+WH+Treg+TR+Byz",
        "extendedStrongs": "G4151",
        "subMeaning": ": spirit»spirit/breath|1_spirit",
        "manuscriptType": "NKO",
        "gloss": "spirit/breath"
      },
      "source": {
        "raw": "Luk.24.39#18=NKO\tπνεῦμα (pneuma)\ta spirit\tG4151G=N-NSN\tπνεῦμα=spirit/breath\tNA28+NA27+Tyn+SBL+WH+Treg+TR+Byz\t\t\tespíritu\t: spirit»spirit/breath|1_spirit\t#18\tG4151\t\t\t\t\t"
      }
    },
    {
      "position": 19,
      "text": "σάρκα",
      "lemma": "σάρξ",
      "morph": "robinson:N-ASF",
      "strongs": [
        "G4561"
      ],
      "translation": "flesh",
      "metadata": {
        "editions": "NA28+NA27+Tyn+SBL+WH+Treg+TR+Byz",
        "extendedStrongs": "G4561",
        "subMeaning": "flesh",
        "manuscriptType": "NKO",
        "gloss": "flesh"
      },
      "source": {
        "raw": "Luk.24.39#19=NKO\tσάρκα (sarka)\tflesh\tG4561=N-ASF\tσάρξ=flesh\tNA28+NA27+Tyn+SBL+WH+Treg+TR+Byz\t\t\tcarne\tflesh\t#19\tG4561\t\t\t\t\t"
      }
    },
    {
      "position": 20,
      "text": "καὶ",
      "lemma": "καί",
      "morph": "robinson:CONJ",
      "strongs": [
        "G2532"
      ],
      "translation": "and",
      "metadata": {
        "editions": "NA28+NA27+Tyn+SBL+WH+Treg+TR+Byz",
        "extendedStrongs": "G2532_C",
        "subMeaning": "and",
        "manuscriptType": "NKO",
        "gloss": "and"
      },
      "source": {
        "raw": "Luk.24.39#20=NKO\tκαὶ (kai)\tand\tG2532=CONJ\tκαί=and\tNA28+NA27+Tyn+SBL+WH+Treg+TR+Byz\t\t\ty\tand\t#20\tG2532_C\t\t\t\t\t"
      }
    },
    {
      "position": 21,
      "text": "ὀστέα",
      "lemma": "ὀστέον",
      "morph": "robinson:N-APN",
      "strongs": [
        "G3747"
      ],
      "translation": "bones",
      "metadata": {
        "editions": "NA28+NA27+Tyn+SBL+WH+Treg+TR+Byz",
        "extendedStrongs": "G3747",
        "subMeaning": "bones",
        "manuscriptType": "NKO",
        "gloss": "bone"
      },
      "source": {
        "raw": "Luk.24.39#21=NKO\tὀστέα (ostea)\tbones\tG3747=N-APN\tὀστέον=bone\tNA28+NA27+Tyn+SBL+WH+Treg+TR+Byz\t\t\thuesos\tbones\t#21\tG3747\t\t\t\t\t"
      }
    },
    {
      "position": 22,
      "text": "οὐκ",
      "lemma": "οὐ",
      "morph": "robinson:PRT-N",
      "strongs": [
        "G3756"
      ],
      "translation": "not",
      "metadata": {
        "editions": "NA28+NA27+Tyn+SBL+WH+Treg+TR+Byz",
        "extendedStrongs": "G3756",
        "subMeaning": "no",
        "manuscriptType": "NKO",
        "gloss": "no"
      },
      "source": {
        "raw": "Luk.24.39#22=NKO\tοὐκ (ouk)\tnot\tG3756=PRT-N\tοὐ=no\tNA28+NA27+Tyn+SBL+WH+Treg+TR+Byz\t\t\tno\tno\t#22»23:G2192\tG3756\t\t\t\t\t"
      }
    },
    {
      "position": 23,
      "text": "ἔχει",
      "lemma": "ἔχω",
      "morph": "robinson:V-PAI-3S",
      "strongs": [
        "G2192"
      ],
      "translation": "has",
      "metadata": {
        "editions": "NA28+NA27+Tyn+SBL+WH+Treg+TR+Byz",
        "extendedStrongs": "G2192_A",
        "subMeaning": "to have",
        "manuscriptType": "NKO",
        "gloss": "to have/be"
      },
      "source": {
        "raw": "Luk.24.39#23=NKO\tἔχει (echei)\thas\tG2192=V-PAI-3S\tἔχω=to have/be\tNA28+NA27+Tyn+SBL+WH+Treg+TR+Byz\t\t\testá teniendo\tto have\t#23\tG2192_A\t\t\t\t\t"
      }
    },
    {
      "position": 24,
      "text": "καθὼς",
      "lemma": "καθώς",
      "morph": "robinson:CONJ",
      "strongs": [
        "G2531"
      ],
      "translation": "even as",
      "metadata": {
        "editions": "NA28+NA27+Tyn+SBL+WH+Treg+TR+Byz",
        "extendedStrongs": "G2531",
        "subMeaning": "as",
        "manuscriptType": "NKO",
        "gloss": "as/just as"
      },
      "source": {
        "raw": "Luk.24.39#24=NKO\tκαθὼς (kathōs)\teven as\tG2531=CONJ\tκαθώς=as/just as\tNA28+NA27+Tyn+SBL+WH+Treg+TR+Byz\t\t\tsegún como\tas\t#24\tG2531\t\t\t\t\t"
      }
    },
    {
      "position": 25,
      "text": "ἐμὲ",
      "lemma": "ἐγώ",
      "morph": "robinson:P-1AS",
      "strongs": [
        "G1473"
      ],
      "translation": "Me myself",
      "metadata": {
        "editions": "NA28+NA27+Tyn+SBL+WH+Treg+TR+Byz",
        "extendedStrongs": "G1473_B",
        "subMeaning": "me",
        "manuscriptType": "NKO",
        "gloss": "I/we"
      },
      "source": {
        "raw": "Luk.24.39#25=NKO\tἐμὲ (eme)\tMe myself\tG1473=P-1AS\tἐγώ=I/we\tNA28+NA27+Tyn+SBL+WH+Treg+TR+Byz\t\t\ta mí\tme\t#25«23:G2192\tG1473_B\tG3165, G1691\t\t\t\t"
      }
    },
    {
      "position": 26,
      "text": "θεωρεῖτε",
      "lemma": "θεωρέω",
      "morph": "robinson:V-PAI-2P",
      "strongs": [
        "G2334"
      ],
      "translation": "you see",
      "metadata": {
        "editions": "NA28+NA27+Tyn+SBL+WH+Treg+TR+Byz",
        "extendedStrongs": "G2334",
        "subMeaning": "to see",
        "manuscriptType": "NKO",
        "gloss": "to see/experience"
      },
      "source": {
        "raw": "Luk.24.39#26=NKO\tθεωρεῖτε (theōreite)\tyou see\tG2334=V-PAI-2P\tθεωρέω=to see/experience\tNA28+NA27+Tyn+SBL+WH+Treg+TR+Byz\t\t\testán contemplando\tto see\t#26\tG2334\t\t\t\t\t"
      }
    },
    {
      "position": 27,
      "text": "ἔχοντα.",
      "lemma": "ἔχω",
      "morph": "robinson:V-PAP-ASM",
      "strongs": [
        "G2192"
      ],
      "translation": "having.",
      "metadata": {
        "editions": "NA28+NA27+Tyn+SBL+WH+Treg+TR+Byz",
        "extendedStrongs": "G2192_B",
        "subMeaning": "to have",
        "manuscriptType": "NKO",
        "gloss": "to have/be"
      },
      "source": {
        "raw": "Luk.24.39#27=NKO\tἔχοντα. (echonta)\thaving.\tG2192=V-PAP-ASM\tἔχω=to have/be\tNA28+NA27+Tyn+SBL+WH+Treg+TR+Byz\t\t\testando teniendo\tto have\t#27\tG2192_B\t\t\t\t\t"
      }
    }
  ]
}