{
  "text": "ἑτέρῳ δὲ πίστις ἐν τῷ αὐτῷ πνεύματι, ἄλλῳ δὲ χαρίσματα ἰαμάτων ἐν τῷ ἑνὶ πνεύματι,",
  "words": [
    {
      "position": 1,
      "text": "ἑτέρῳ",
      "lemma": [
        "G2087"
      ],
      "morph": "robinson:A-DSM",
      "strongs": "G2087",
      "translation": "to a different one",
      "metadata": {},
      "gematria": {
        "standard": 1220,
        "ordinal": 79,
        "reduced": 5
      }
    },
    {
      "position": 2,
      "text": "δὲ",
      "lemma": [
        "G1161"
      ],
      "morph": "robinson:CONJ",
      "strongs": "G1161",
      "translation": "now",
      "metadata": {},
      "gematria": {
        "standard": 9,
        "ordinal": 9,
        "reduced": 9
      }
    },
    {
      "position": 3,
      "text": "πίστις",
      "lemma": [
        "G4102G"
      ],
      "morph": "robinson:N-NSF",
      "strongs": "G4102G",
      "translation": "faith",
      "metadata": {},
      "gematria": {
        "standard": 800,
        "ordinal": 89,
        "reduced": 8
      }
    },
    {
      "position": 4,
      "text": "ἐν",
      "lemma": [
        "G1722"
      ],
      "morph": "robinson:PREP",
      "strongs": "G1722",
      "translation": "by",
      "metadata": {},
      "gematria": {
        "standard": 55,
        "ordinal": 18,
        "reduced": 1
      }
    },
    {
      "position": 5,
      "text": "τῷ",
      "lemma": [
        "G3588"
      ],
      "morph": "robinson:T-DSN",
      "strongs": "G3588",
      "translation": "the",
      "metadata": {},
      "gematria": {
        "standard": 1110,
        "ordinal": 52,
        "reduced": 3
      }
    },
    {
      "position": 6,
      "text": "αὐτῷ",
      "lemma": [
        "G0846"
      ],
      "morph": "robinson:P-DSN",
      "strongs": "G0846",
      "translation": "same",
      "metadata": {},
      "gematria": {
        "standard": 1511,
        "ordinal": 73,
        "reduced": 8
      }
    },
    {
      "position": 7,
      "text": "πνεύματι,",
      "lemma": [
        "G4151G"
      ],
      "morph": "robinson:N-DSN",
      "strongs": "G4151G",
      "translation": "Spirit,",
      "metadata": {},
      "gematria": {
        "standard": 886,
        "ordinal": 95,
        "reduced": 4
      }
    },
    {
      "position": 8,
      "text": "ἄλλῳ",
      "lemma": [
        "G0243"
      ],
      "morph": "robinson:A-DSM",
      "strongs": "G0243",
      "translation": "to another",
      "metadata": {},
      "gematria": {
        "standard": 871,
        "ordinal": 56,
        "reduced": 7
      }
    },
    {
      "position": 9,
      "text": "δὲ",
      "lemma": [
        "G1161"
      ],
      "morph": "robinson:CONJ",
      "strongs": "G1161",
      "translation": "now",
      "metadata": {},
      "gematria": {
        "standard": 9,
        "ordinal": 9,
        "reduced": 9
      }
    },
    {
      "position": 10,
      "text": "χαρίσματα",
      "lemma": [
        "G5486"
      ],
      "morph": "robinson:N-NPN",
      "strongs": "G5486",
      "translation": "gifts",
      "metadata": {},
      "gematria": {
        "standard": 1253,
        "ordinal": 100,
        "reduced": 2
      }
    },
    {
      "position": 11,
      "text": "ἰαμάτων",
      "lemma": [
        "G2386"
      ],
      "morph": "robinson:N-GPN",
      "strongs": "G2386",
      "translation": "of healing",
      "metadata": {},
      "gematria": {
        "standard": 1202,
        "ordinal": 79,
        "reduced": 5
      }
    },
    {
      "position": 12,
      "text": "ἐν",
      "lemma": [
        "G1722"
      ],
      "morph": "robinson:PREP",
      "strongs": "G1722",
      "translation": "in",
      "metadata": {},
      "gematria": {
        "standard": 55,
        "ordinal": 18,
        "reduced": 1
      }
    },
    {
      "position": 13,
      "text": "τῷ",
      "lemma": [
        "G3588"
      ],
      "morph": "robinson:T-DSN",
      "strongs": "G3588",
      "translation": "that",
      "metadata": {},
      "gematria": {
        "standard": 1110,
        "ordinal": 52,
        "reduced": 3
      }
    },
    {
      "position": 14,
      "text": "ἑνὶ",
      "lemma": [
        "G1520"
      ],
      "morph": "robinson:A-DSN",
      "strongs": "G1520",
      "translation": "one",
      "metadata": {},
      "gematria": {
        "standard": 65,
        "ordinal": 27,
        "reduced": 2
      }
    },
    {
      "position": 15,
      "text": "πνεύματι,",
      "lemma": [
        "G4151G"
      ],
      "morph": "robinson:N-DSN",
      "strongs": "G4151G",
      "translation": "Spirit,",
      "metadata": {},
      "gematria": {
        "standard": 886,
        "ordinal": 95,
        "reduced": 4
      }
    }
  ],
  "gematria": {
    "standard": 11042,
    "ordinal": 851,
    "reduced": 71
  }
}