{
  "text": "ἀλλ᾽ ἀποταξάμενος αὐτοῖς εἰπών δεῖ με πάντως τὴν ἑορτὴν τὴν ἐρχομένην ποιῆσαι εἰς Ἱεροσόλυμα· πάλιν δὲ ἀνακάμψω πρὸς ὑμᾶς τοῦ θεοῦ θέλοντος, καὶ ἀνήχθη ἀπὸ τῆς Ἐφέσου.",
  "words": [
    {
      "position": 1,
      "text": "ἀλλ᾽",
      "lemma": "ἀλλά",
      "morph": "robinson:CONJ",
      "strongs": [
        "G0235"
      ],
      "translation": "but",
      "metadata": {
        "editions": "NA28+NA27+Tyn+SBL+WH+Treg+TR»2+Byz»2",
        "extendedStrongs": "G0235",
        "subMeaning": "but",
        "variants": "NA27+Tyn+SBL+WH+Treg: ἀλλὰ ;",
        "manuscriptType": "NKO",
        "gloss": "but"
      },
      "source": {
        "raw": "Act.18.21#01=NKO\tἀλλ᾽ (all᾽)\tbut\tG0235=CONJ\tἀλλά=but\tNA28+NA27+Tyn+SBL+WH+Treg+TR»2+Byz»2\t\tNA27+Tyn+SBL+WH+Treg: ἀλλὰ ; \tsino\tbut\t#01\tG0235\t\t\t\t\t"
      }
    },
    {
      "position": 2,
      "text": "ἀποταξάμενος",
      "lemma": "ἀποτάσσω",
      "morph": "robinson:V-AMP-NSM",
      "strongs": [
        "G0657"
      ],
      "translation": "having taken leave",
      "metadata": {
        "editions": "NA28+NA27+Tyn+SBL+WH+Treg",
        "extendedStrongs": "G0657",
        "subMeaning": "to leave",
        "variants": "ἀπετάξατο (t=apetaxato) took leave - G0657=V-ADI-3S in: TR»1+Byz»1",
        "manuscriptType": "N(k)O",
        "gloss": "to leave"
      },
      "source": {
        "raw": "Act.18.21#02=N(k)O\tἀποταξάμενος (apotaxamenos)\thaving taken leave\tG0657=V-AMP-NSM\tἀποτάσσω=to leave\tNA28+NA27+Tyn+SBL+WH+Treg\tἀπετάξατο (t=apetaxato) took leave - G0657=V-ADI-3S in: TR»1+Byz»1\t\thabiendo separado de sí\tto leave\t#02\tG0657\t\t\t\t\t"
      }
    },
    {
      "position": 3,
      "text": "αὐτοῖς",
      "lemma": "αὐτός",
      "morph": "robinson:P-DPM",
      "strongs": [
        "G0846"
      ],
      "translation": "to them",
      "metadata": {
        "editions": "TR+Byz",
        "extendedStrongs": "G0846",
        "subMeaning": "to them",
        "manuscriptType": "k",
        "gloss": "he/she/it/self"
      },
      "source": {
        "raw": "Act.18.21#04=k\tαὐτοῖς (autois)\tto them\tG0846=P-DPM\tαὐτός=he/she/it/self\tTR+Byz\t\t\ta ellos\tto them\t#04«02:G0657\tG0846\tG3778\t\t\t\t"
      }
    },
    {
      "position": 4,
      "text": "εἰπών",
      "lemma": "ἔπω, ἐρῶ, εἶπον",
      "morph": "robinson:V-2AAP-NSM",
      "strongs": [
        "G2036"
      ],
      "translation": "having said",
      "metadata": {
        "editions": "NA28+NA27+Tyn+SBL+WH+Treg+TR+Byz",
        "extendedStrongs": "G2036",
        "subMeaning": "to say",
        "manuscriptType": "NKO",
        "gloss": "to say"
      },
      "source": {
        "raw": "Act.18.21#05=NKO\tεἰπών (eipōn)\thaving said\tG2036=V-2AAP-NSM\tἔπω, ἐρῶ, εἶπον=to say\tNA28+NA27+Tyn+SBL+WH+Treg+TR+Byz\t\t\thabiendo dicho\tto say\t#05\tG2036\t\t\t\t\t"
      }
    },
    {
      "position": 5,
      "text": "δεῖ",
      "lemma": "δεῖ",
      "morph": "robinson:V-PAI-3S",
      "strongs": [
        "G1163"
      ],
      "translation": "necessary",
      "metadata": {
        "editions": "TR+Byz",
        "extendedStrongs": "G1163",
        "subMeaning": "be necessary",
        "manuscriptType": "KO",
        "gloss": "be necessary"
      },
      "source": {
        "raw": "Act.18.21#06=KO\tδεῖ (dei)\tnecessary\tG1163=V-PAI-3S\tδεῖ=be necessary\tTR+Byz\t\t\testá siendo necesario\tbe necessary\t#06\tG1163\t\t^ \t\t\t"
      }
    },
    {
      "position": 6,
      "text": "με",
      "lemma": "ἐγώ",
      "morph": "robinson:P-1AS",
      "strongs": [
        "G3165"
      ],
      "translation": "me",
      "metadata": {
        "editions": "TR+Byz",
        "extendedStrongs": "G3165",
        "subMeaning": "me",
        "manuscriptType": "K",
        "gloss": "I/we"
      },
      "source": {
        "raw": "Act.18.21#07=K\tμε (me)\tme\tG3165=P-1AS\tἐγώ=I/we\tTR+Byz\t\t\ta mí\tme\t#07«06:G1163\tG3165\t\t^ \t\t\t"
      }
    },
    {
      "position": 7,
      "text": "πάντως",
      "lemma": "πάντως",
      "morph": "robinson:ADV",
      "strongs": [
        "G3843"
      ],
      "translation": "by all means",
      "metadata": {
        "editions": "TR+Byz",
        "extendedStrongs": "G3843",
        "subMeaning": "surely",
        "manuscriptType": "K",
        "gloss": "surely"
      },
      "source": {
        "raw": "Act.18.21#08=K\tπάντως (pantōs)\tby all means\tG3843=ADV\tπάντως=surely\tTR+Byz\t\t\tde todas maneras\tsurely\t#08\tG3843\t\t^ \t\t\t"
      }
    },
    {
      "position": 8,
      "text": "τὴν",
      "lemma": "ὁ",
      "morph": "robinson:T-ASF",
      "strongs": [
        "G3588"
      ],
      "translation": "the",
      "metadata": {
        "editions": "TR+Byz",
        "extendedStrongs": "G3588_a",
        "subMeaning": "the",
        "manuscriptType": "K",
        "gloss": "the/this/who"
      },
      "source": {
        "raw": "Act.18.21#09=K\tτὴν (tēn)\tthe\tG3588=T-ASF\tὁ=the/this/who\tTR+Byz\t\t\tla\tthe\t#09»10:G1859\tG3588_a\t\t^ \t\t\t"
      }
    },
    {
      "position": 9,
      "text": "ἑορτὴν",
      "lemma": "ἑορτή",
      "morph": "robinson:N-ASF",
      "strongs": [
        "G1859"
      ],
      "translation": "feast",
      "metadata": {
        "editions": "TR+Byz",
        "extendedStrongs": "G1859",
        "subMeaning": "festival",
        "manuscriptType": "K",
        "gloss": "festival"
      },
      "source": {
        "raw": "Act.18.21#10=K\tἑορτὴν (he'ortēn)\tfeast\tG1859=N-ASF\tἑορτή=festival\tTR+Byz\t\t\tfiesta\tfestival\t#10\tG1859\t\t^ \t\t\t"
      }
    },
    {
      "position": 10,
      "text": "τὴν",
      "lemma": "ὁ",
      "morph": "robinson:T-ASF",
      "strongs": [
        "G3588"
      ],
      "translation": "which",
      "metadata": {
        "editions": "TR+Byz",
        "extendedStrongs": "G3588_b",
        "subMeaning": "[that] which",
        "manuscriptType": "K",
        "gloss": "the/this/who"
      },
      "source": {
        "raw": "Act.18.21#11=K\tτὴν (tēn)\twhich\tG3588=T-ASF\tὁ=the/this/who\tTR+Byz\t\t\tla\t[that] which\t#11»12:G2064\tG3588_b\t\t^ \t\t\t"
      }
    },
    {
      "position": 11,
      "text": "ἐρχομένην",
      "lemma": "ἔρχομαι",
      "morph": "robinson:V-PNP-ASF",
      "strongs": [
        "G2064"
      ],
      "translation": "is coming",
      "metadata": {
        "editions": "TR+Byz",
        "extendedStrongs": "G2064",
        "subMeaning": "to come",
        "manuscriptType": "K",
        "gloss": "to come/go"
      },
      "source": {
        "raw": "Act.18.21#12=K\tἐρχομένην (erchomenēn)\tis coming\tG2064=V-PNP-ASF\tἔρχομαι=to come/go\tTR+Byz\t\t\testando viniendo\tto come\t#12\tG2064\t\t^ \t\t\t"
      }
    },
    {
      "position": 12,
      "text": "ποιῆσαι",
      "lemma": "ποιέω",
      "morph": "robinson:V-AAN",
      "strongs": [
        "G4160G"
      ],
      "translation": "to do",
      "metadata": {
        "editions": "TR+Byz",
        "extendedStrongs": "G4160",
        "subMeaning": ": do»to do/make|1_do/work",
        "manuscriptType": "K",
        "gloss": "to do/make"
      },
      "source": {
        "raw": "Act.18.21#13=K\tποιῆσαι (poiēsai)\tto do\tG4160G=V-AAN\tποιέω=to do/make\tTR+Byz\t\t\thacer\t: do»to do/make|1_do/work\t#13\tG4160\t\t^ \t\t\t"
      }
    },
    {
      "position": 13,
      "text": "εἰς",
      "lemma": "εἰς",
      "morph": "robinson:PREP",
      "strongs": [
        "G1519"
      ],
      "translation": "into",
      "metadata": {
        "editions": "TR+Byz",
        "extendedStrongs": "G1519",
        "subMeaning": "toward",
        "manuscriptType": "K",
        "gloss": "toward"
      },
      "source": {
        "raw": "Act.18.21#14=K\tεἰς (eis)\tinto\tG1519=PREP\tεἰς=toward\tTR+Byz\t\t\thacia dentro\ttoward\t#14\tG1519\t\t^ \t\t\t"
      }
    },
    {
      "position": 14,
      "text": "Ἱεροσόλυμα·",
      "lemma": "Ἱεροσόλυμα",
      "morph": "robinson:N-APN-L",
      "strongs": [
        "G2414"
      ],
      "translation": "Jerusalem;",
      "metadata": {
        "editions": "TR+Byz",
        "extendedStrongs": "G2414",
        "subMeaning": "Jerusalem»Jerusalem|Jerusalem@Jos.10.1",
        "manuscriptType": "K",
        "gloss": "Jerusalem"
      },
      "source": {
        "raw": "Act.18.21#15=K\tἹεροσόλυμα· (Hi'erosoluma)\tJerusalem;\tG2414=N-APN-L\tἹεροσόλυμα=Jerusalem\tTR+Byz\t\t\tJerusalén\tJerusalem»Jerusalem|Jerusalem@Jos.10.1\t#15\tG2414\t\t^ δεῖ   με    πάντως    τὴν    ἑορτὴν    τὴν    ἐρχομένην    ποιῆσαι    εἰς    Ἱεροσόλυμα·   (<i>dei me pantōs tēn he'ortēn tēn erchomenēn poiēsai eis Hi'erosoluma</i>) 'necessary me by all means the feast which is coming to do into Jerusalem;' is only in traditional manuscripts (TR+Byz)\t\t\t"
      }
    },
    {
      "position": 15,
      "text": "πάλιν",
      "lemma": "πάλιν",
      "morph": "robinson:ADV",
      "strongs": [
        "G3825"
      ],
      "translation": "Again",
      "metadata": {
        "editions": "NA28+NA27+Tyn+SBL+WH+Treg+TR+Byz",
        "extendedStrongs": "G3825",
        "subMeaning": "again",
        "manuscriptType": "NKO",
        "gloss": "again"
      },
      "source": {
        "raw": "Act.18.21#16=NKO\tπάλιν (palin)\tAgain\tG3825=ADV\tπάλιν=again\tNA28+NA27+Tyn+SBL+WH+Treg+TR+Byz\t\t\tOtra vez\tagain\t#16\tG3825\t\t\t\t\t"
      }
    },
    {
      "position": 16,
      "text": "δὲ",
      "lemma": "δέ",
      "morph": "robinson:CONJ",
      "strongs": [
        "G1161"
      ],
      "translation": "now",
      "metadata": {
        "editions": "TR+Byz",
        "extendedStrongs": "G1161",
        "subMeaning": "and",
        "manuscriptType": "k",
        "gloss": "but/and"
      },
      "source": {
        "raw": "Act.18.21#17=k\tδὲ (de)\tnow\tG1161=CONJ\tδέ=but/and\tTR+Byz\t\t\tpero\tand\t#17\tG1161\t\t\t\t\t"
      }
    },
    {
      "position": 17,
      "text": "ἀνακάμψω",
      "lemma": "ἀνακάμπτω",
      "morph": "robinson:V-FAI-1S",
      "strongs": [
        "G0344"
      ],
      "translation": "I will return",
      "metadata": {
        "editions": "NA28+NA27+Tyn+SBL+WH+Treg+TR+Byz",
        "extendedStrongs": "G0344",
        "subMeaning": "to return",
        "manuscriptType": "NKO",
        "gloss": "to return"
      },
      "source": {
        "raw": "Act.18.21#18=NKO\tἀνακάμψω (anakampsō)\tI will return\tG0344=V-FAI-1S\tἀνακάμπτω=to return\tNA28+NA27+Tyn+SBL+WH+Treg+TR+Byz\t\t\tvolveré\tto return\t#18\tG0344\t\t\t\t\t"
      }
    },
    {
      "position": 18,
      "text": "πρὸς",
      "lemma": "πρός",
      "morph": "robinson:PREP",
      "strongs": [
        "G4314"
      ],
      "translation": "to",
      "metadata": {
        "editions": "NA28+NA27+Tyn+SBL+WH+Treg+TR+Byz",
        "extendedStrongs": "G4314",
        "subMeaning": "to",
        "manuscriptType": "NKO",
        "gloss": "to/with"
      },
      "source": {
        "raw": "Act.18.21#19=NKO\tπρὸς (pros)\tto\tG4314=PREP\tπρός=to/with\tNA28+NA27+Tyn+SBL+WH+Treg+TR+Byz\t\t\thacia\tto\t#19\tG4314\t\t\t\t\t"
      }
    },
    {
      "position": 19,
      "text": "ὑμᾶς",
      "lemma": "σύ",
      "morph": "robinson:P-2AP",
      "strongs": [
        "G4771"
      ],
      "translation": "you",
      "metadata": {
        "editions": "NA28+NA27+Tyn+SBL+WH+Treg+TR+Byz",
        "extendedStrongs": "G4771",
        "subMeaning": "you",
        "manuscriptType": "NKO",
        "gloss": "you"
      },
      "source": {
        "raw": "Act.18.21#20=NKO\tὑμᾶς (humas)\tyou\tG4771=P-2AP\tσύ=you\tNA28+NA27+Tyn+SBL+WH+Treg+TR+Byz\t\t\ta ustedes\tyou\t#20«19:G4314\tG4771\tG5209\t\t\t\t"
      }
    },
    {
      "position": 20,
      "text": "τοῦ",
      "lemma": "ὁ",
      "morph": "robinson:T-GSM",
      "strongs": [
        "G3588"
      ],
      "translation": "<the>",
      "metadata": {
        "editions": "NA28+NA27+Tyn+SBL+WH+Treg+TR+Byz",
        "extendedStrongs": "G3588_C",
        "subMeaning": "the",
        "manuscriptType": "NKO",
        "gloss": "the/this/who"
      },
      "source": {
        "raw": "Act.18.21#21=NKO\tτοῦ (tou)\t<the>\tG3588=T-GSM\tὁ=the/this/who\tNA28+NA27+Tyn+SBL+WH+Treg+TR+Byz\t\t\tde el\tthe\t#21»22:G2316\tG3588_C\t\t\t\t\t"
      }
    },
    {
      "position": 21,
      "text": "θεοῦ",
      "lemma": "θεός",
      "morph": "robinson:N-GSM-T",
      "strongs": [
        "G2316"
      ],
      "translation": "God",
      "metadata": {
        "editions": "NA28+NA27+Tyn+SBL+WH+Treg+TR+Byz",
        "extendedStrongs": "G2316",
        "subMeaning": "God",
        "manuscriptType": "NKO",
        "gloss": "God"
      },
      "source": {
        "raw": "Act.18.21#22=NKO\tθεοῦ (theou)\tGod\tG2316=N-GSM-T\tθεός=God\tNA28+NA27+Tyn+SBL+WH+Treg+TR+Byz\t\t\tDios\tGod\t#22\tG2316\t\t\t\t\t"
      }
    },
    {
      "position": 22,
      "text": "θέλοντος,",
      "lemma": "θέλω",
      "morph": "robinson:V-PAP-GSM",
      "strongs": [
        "G2309"
      ],
      "translation": "willing,",
      "metadata": {
        "editions": "NA28+NA27+Tyn+SBL+WH+Treg+TR+Byz",
        "extendedStrongs": "G2309",
        "subMeaning": "to will",
        "manuscriptType": "NKO",
        "gloss": "to will/desire"
      },
      "source": {
        "raw": "Act.18.21#23=NKO\tθέλοντος, (thelontos)\twilling,\tG2309=V-PAP-GSM\tθέλω=to will/desire\tNA28+NA27+Tyn+SBL+WH+Treg+TR+Byz\t\t\testando queriendo\tto will\t#23\tG2309\t\t\t\t\t"
      }
    },
    {
      "position": 23,
      "text": "καὶ",
      "lemma": "καί",
      "morph": "robinson:CONJ",
      "strongs": [
        "G2532"
      ],
      "translation": "and",
      "metadata": {
        "editions": "TR",
        "extendedStrongs": "G2532_b",
        "subMeaning": "and",
        "manuscriptType": "k",
        "gloss": "and"
      },
      "source": {
        "raw": "Act.18.21#24=k\tκαὶ (kai)\tand\tG2532=CONJ\tκαί=and\tTR\t\t\ty\tand\t#24\tG2532_b\t\t\t\t\t"
      }
    },
    {
      "position": 24,
      "text": "ἀνήχθη",
      "lemma": "ἀνάγω",
      "morph": "robinson:V-API-3S",
      "strongs": [
        "G0321"
      ],
      "translation": "he sailed",
      "metadata": {
        "editions": "NA28+NA27+Tyn+SBL+WH+Treg+TR+Byz",
        "extendedStrongs": "G0321",
        "subMeaning": "to lead",
        "manuscriptType": "NKO",
        "gloss": "to lead"
      },
      "source": {
        "raw": "Act.18.21#25=NKO\tἀνήχθη (anēchthē)\the sailed\tG0321=V-API-3S\tἀνάγω=to lead\tNA28+NA27+Tyn+SBL+WH+Treg+TR+Byz\t\t\tFue conducido hacia arriba\tto lead\t#25\tG0321\t\t\t\t\t"
      }
    },
    {
      "position": 25,
      "text": "ἀπὸ",
      "lemma": "ἀπό",
      "morph": "robinson:PREP",
      "strongs": [
        "G0575"
      ],
      "translation": "from",
      "metadata": {
        "editions": "NA28+NA27+Tyn+SBL+WH+Treg+TR+Byz",
        "extendedStrongs": "G0575",
        "subMeaning": "from",
        "manuscriptType": "NKO",
        "gloss": "away from"
      },
      "source": {
        "raw": "Act.18.21#26=NKO\tἀπὸ (apo)\tfrom\tG0575=PREP\tἀπό=away from\tNA28+NA27+Tyn+SBL+WH+Treg+TR+Byz\t\t\tdesde\tfrom\t#26\tG0575\t\t\t\t\t"
      }
    },
    {
      "position": 26,
      "text": "τῆς",
      "lemma": "ὁ",
      "morph": "robinson:T-GSF",
      "strongs": [
        "G3588"
      ],
      "translation": "<the>",
      "metadata": {
        "editions": "NA28+NA27+Tyn+SBL+WH+Treg+TR+Byz",
        "extendedStrongs": "G3588_D",
        "subMeaning": "the",
        "manuscriptType": "NKO",
        "gloss": "the/this/who"
      },
      "source": {
        "raw": "Act.18.21#27=NKO\tτῆς (tēs)\t<the>\tG3588=T-GSF\tὁ=the/this/who\tNA28+NA27+Tyn+SBL+WH+Treg+TR+Byz\t\t\tla\tthe\t#27»28:G2181\tG3588_D\t\t\t\t\t"
      }
    },
    {
      "position": 27,
      "text": "Ἐφέσου.",
      "lemma": "Ἔφεσος",
      "morph": "robinson:N-GSF-L",
      "strongs": [
        "G2181"
      ],
      "translation": "Ephesus.",
      "metadata": {
        "editions": "NA28+NA27+Tyn+SBL+WH+Treg+TR+Byz",
        "extendedStrongs": "G2181",
        "subMeaning": "Ephesus»Ephesus|Ephesus@Act.18.19",
        "manuscriptType": "NKO",
        "gloss": "Ephesus"
      },
      "source": {
        "raw": "Act.18.21#28=NKO\tἘφέσου. (Ephesou)\tEphesus.\tG2181=N-GSF-L\tἜφεσος=Ephesus\tNA28+NA27+Tyn+SBL+WH+Treg+TR+Byz\t\t\tÉfeso\tEphesus»Ephesus|Ephesus@Act.18.19\t#28\tG2181\t\t\t\t\t"
      }
    }
  ]
}