{
  "text": "ὁ διὰ στόματος Δαυὶδ τοῦ παιδός σου εἰπών· ἱνατί ἐφρύαξαν ἔθνη καὶ λαοὶ ἐμελέτησαν κενά;",
  "words": [
    {
      "position": 1,
      "text": "ὁ",
      "lemma": [
        "G3588"
      ],
      "morph": "robinson:T-NSM",
      "strongs": "G3588",
      "translation": "who",
      "metadata": {},
      "gematria": {
        "standard": 70,
        "ordinal": 15,
        "reduced": 7
      }
    },
    {
      "position": 2,
      "text": "διὰ",
      "lemma": [
        "G1223"
      ],
      "morph": "robinson:PREP",
      "strongs": "G1223",
      "translation": "through",
      "metadata": {},
      "gematria": {
        "standard": 15,
        "ordinal": 14,
        "reduced": 6
      }
    },
    {
      "position": 3,
      "text": "στόματος",
      "lemma": [
        "G4750"
      ],
      "morph": "robinson:N-GSN",
      "strongs": "G4750",
      "translation": "through [the] mouth",
      "metadata": {},
      "gematria": {
        "standard": 1181,
        "ordinal": 117,
        "reduced": 2
      }
    },
    {
      "position": 4,
      "text": "Δαυὶδ",
      "lemma": [
        "G1138"
      ],
      "morph": "robinson:N-GSM-P",
      "strongs": "G1138",
      "translation": "of David",
      "metadata": {},
      "gematria": {
        "standard": 419,
        "ordinal": 38,
        "reduced": 5
      }
    },
    {
      "position": 5,
      "text": "τοῦ",
      "lemma": [
        "G3588"
      ],
      "morph": "robinson:T-GSM",
      "strongs": "G3588",
      "translation": "the",
      "metadata": {},
      "gematria": {
        "standard": 770,
        "ordinal": 54,
        "reduced": 5
      }
    },
    {
      "position": 6,
      "text": "παιδός",
      "lemma": [
        "G3816"
      ],
      "morph": "robinson:N-GSM",
      "strongs": "G3816",
      "translation": "servant",
      "metadata": {},
      "gematria": {
        "standard": 365,
        "ordinal": 63,
        "reduced": 5
      }
    },
    {
      "position": 7,
      "text": "σου",
      "lemma": [
        "G4771"
      ],
      "morph": "robinson:P-2GS",
      "strongs": "G4771",
      "translation": "of You",
      "metadata": {},
      "gematria": {
        "standard": 670,
        "ordinal": 53,
        "reduced": 4
      }
    },
    {
      "position": 8,
      "text": "εἰπών·",
      "lemma": [
        "G2036"
      ],
      "morph": "robinson:V-2AAP-NSM",
      "strongs": "G2036",
      "translation": "having spoken:",
      "metadata": {},
      "gematria": {
        "standard": 945,
        "ordinal": 67,
        "reduced": 9
      }
    },
    {
      "position": 9,
      "text": "ἱνατί",
      "lemma": [
        "G2443"
      ],
      "morph": "robinson:CONJ + G5101",
      "strongs": "G2443",
      "translation": "so why",
      "metadata": {},
      "gematria": {
        "standard": 371,
        "ordinal": 51,
        "reduced": 2
      }
    },
    {
      "position": 10,
      "text": "ἐφρύαξαν",
      "lemma": [
        "G5433"
      ],
      "morph": "robinson:V-AAI-3P",
      "strongs": "G5433",
      "translation": "did rage",
      "metadata": {},
      "gematria": {
        "standard": 1117,
        "ordinal": 92,
        "reduced": 1
      }
    },
    {
      "position": 11,
      "text": "ἔθνη",
      "lemma": [
        "G1484"
      ],
      "morph": "robinson:N-NPN",
      "strongs": "G1484",
      "translation": "[the] Gentiles",
      "metadata": {},
      "gematria": {
        "standard": 72,
        "ordinal": 33,
        "reduced": 9
      }
    },
    {
      "position": 12,
      "text": "καὶ",
      "lemma": [
        "G2532"
      ],
      "morph": "robinson:CONJ",
      "strongs": "G2532",
      "translation": "and",
      "metadata": {},
      "gematria": {
        "standard": 31,
        "ordinal": 20,
        "reduced": 4
      }
    },
    {
      "position": 13,
      "text": "λαοὶ",
      "lemma": [
        "G2992"
      ],
      "morph": "robinson:N-NPM",
      "strongs": "G2992",
      "translation": "peoples",
      "metadata": {},
      "gematria": {
        "standard": 111,
        "ordinal": 36,
        "reduced": 3
      }
    },
    {
      "position": 14,
      "text": "ἐμελέτησαν",
      "lemma": [
        "G3191"
      ],
      "morph": "robinson:V-AAI-3P",
      "strongs": "G3191",
      "translation": "did devise",
      "metadata": {},
      "gematria": {
        "standard": 644,
        "ordinal": 96,
        "reduced": 5
      }
    },
    {
      "position": 15,
      "text": "κενά;",
      "lemma": [
        "G2756"
      ],
      "morph": "robinson:A-APN",
      "strongs": "G2756",
      "translation": "vain things?",
      "metadata": {},
      "gematria": {
        "standard": 76,
        "ordinal": 29,
        "reduced": 4
      }
    }
  ],
  "gematria": {
    "standard": 6857,
    "ordinal": 778,
    "reduced": 71
  }
}